RsSmab/RsSmab.py
RsSmab/__init__.py
RsSmab/enums.py
RsSmab/repcap.py
RsSmab/CustomFiles/__init__.py
RsSmab/CustomFiles/events.py
RsSmab/CustomFiles/utilities.py
RsSmab/Implementations/FormatPy.py
RsSmab/Implementations/Kboard.py
RsSmab/Implementations/Memory.py
RsSmab/Implementations/Sweep.py
RsSmab/Implementations/Unit.py
RsSmab/Implementations/__init__.py
RsSmab/Implementations/Calculate/__init__.py
RsSmab/Implementations/Calculate/Power/__init__.py
RsSmab/Implementations/Calculate/Power/Sweep/__init__.py
RsSmab/Implementations/Calculate/Power/Sweep/Frequency/__init__.py
RsSmab/Implementations/Calculate/Power/Sweep/Frequency/Marker/Feed.py
RsSmab/Implementations/Calculate/Power/Sweep/Frequency/Marker/State.py
RsSmab/Implementations/Calculate/Power/Sweep/Frequency/Marker/__init__.py
RsSmab/Implementations/Calculate/Power/Sweep/Frequency/Math/State.py
RsSmab/Implementations/Calculate/Power/Sweep/Frequency/Math/Subtract.py
RsSmab/Implementations/Calculate/Power/Sweep/Frequency/Math/Xval.py
RsSmab/Implementations/Calculate/Power/Sweep/Frequency/Math/Yval.py
RsSmab/Implementations/Calculate/Power/Sweep/Frequency/Math/__init__.py
RsSmab/Implementations/Calculate/Power/Sweep/Power/__init__.py
RsSmab/Implementations/Calculate/Power/Sweep/Power/Marker/Feed.py
RsSmab/Implementations/Calculate/Power/Sweep/Power/Marker/State.py
RsSmab/Implementations/Calculate/Power/Sweep/Power/Marker/__init__.py
RsSmab/Implementations/Calculate/Power/Sweep/Power/Math/State.py
RsSmab/Implementations/Calculate/Power/Sweep/Power/Math/Subtract.py
RsSmab/Implementations/Calculate/Power/Sweep/Power/Math/Xval.py
RsSmab/Implementations/Calculate/Power/Sweep/Power/Math/Yval.py
RsSmab/Implementations/Calculate/Power/Sweep/Power/Math/__init__.py
RsSmab/Implementations/Calculate/Power/Sweep/Time/__init__.py
RsSmab/Implementations/Calculate/Power/Sweep/Time/Gate/Average.py
RsSmab/Implementations/Calculate/Power/Sweep/Time/Gate/Feed.py
RsSmab/Implementations/Calculate/Power/Sweep/Time/Gate/Maximum.py
RsSmab-5.30.133.dist-info/METADATA
RsSmab-5.30.133.dist-info/WHEEL
RsSmab-5.30.133.dist-info/top_level.txt
RsSmab-5.30.133.dist-info/RECORD
